fmu/__init__.py
fmu/dataio/__init__.py
fmu/dataio/_definitions.py
fmu/dataio/_logging.py
fmu/dataio/_metadata.py
fmu/dataio/_runcontext.py
fmu/dataio/_utils.py
fmu/dataio/aggregation.py
fmu/dataio/case.py
fmu/dataio/dataio.py
fmu/dataio/exceptions.py
fmu/dataio/preprocessed.py
fmu/dataio/py.typed
fmu/dataio/types.py
fmu/dataio/version.py
fmu/dataio/_readers/__init__.py
fmu/dataio/_readers/faultroom.py
fmu/dataio/_readers/tsurf.py
fmu/dataio/export/__init__.py
fmu/dataio/export/_base.py
fmu/dataio/export/_decorators.py
fmu/dataio/export/_export_result.py
fmu/dataio/export/rms/__init__.py
fmu/dataio/export/rms/_base.py
fmu/dataio/export/rms/_conditional_rms_imports.py
fmu/dataio/export/rms/_utils.py
fmu/dataio/export/rms/field_outline.py
fmu/dataio/export/rms/fluid_contact_outlines.py
fmu/dataio/export/rms/fluid_contact_surfaces.py
fmu/dataio/export/rms/inplace_volumes.py
fmu/dataio/export/rms/structure_depth_fault_lines.py
fmu/dataio/export/rms/structure_depth_fault_surfaces.py
fmu/dataio/export/rms/structure_depth_isochores.py
fmu/dataio/export/rms/structure_depth_surfaces.py
fmu/dataio/export/rms/structure_time_surfaces.py
fmu/dataio/external_interfaces/schema_validation_interface.py
fmu/dataio/external_interfaces/sumo_explorer_interface.py
fmu/dataio/hook_implementations/jobs.py
fmu/dataio/load/__init__.py
fmu/dataio/load/load_standard_results.py
fmu/dataio/manifest/__init__.py
fmu/dataio/manifest/_manifest.py
fmu/dataio/manifest/_models.py
fmu/dataio/providers/__init__.py
fmu/dataio/providers/_base.py
fmu/dataio/providers/_filedata.py
fmu/dataio/providers/_fmu.py
fmu/dataio/providers/objectdata/__init__.py
fmu/dataio/providers/objectdata/_base.py
fmu/dataio/providers/objectdata/_export_models.py
fmu/dataio/providers/objectdata/_faultroom.py
fmu/dataio/providers/objectdata/_provider.py
fmu/dataio/providers/objectdata/_tables.py
fmu/dataio/providers/objectdata/_triangulated_surface.py
fmu/dataio/providers/objectdata/_utils.py
fmu_dataio-2.20.0.dist-info/licenses/LICENSE
fmu_dataio-2.20.0.dist-info/METADATA
fmu_dataio-2.20.0.dist-info/WHEEL
fmu_dataio-2.20.0.dist-info/entry_points.txt
fmu_dataio-2.20.0.dist-info/top_level.txt
fmu_dataio-2.20.0.dist-info/RECORD
