Metadata-Version: 2.4
Name: fmu-dataio
Version: 2.20.0
Summary: Facilitate data io in FMU with rich metadata
Author-email: Equinor <xxxxx@equinor.com>
License: Apache 2.0
Project-URL: Homepage, https://github.com/equinor/fmu-dataio
Project-URL: Repository, https://github.com/equinor/fmu-dataio
Project-URL: Issues, https://github.com/equinor/fmu-dataio/issues
Project-URL: Documentation, https://fmu-dataio.readthedocs.io
Keywords: fmu,sumo
Classifier: Development Status :: 5 - Production/Stable
Classifier: Intended Audience :: Developers
Classifier: Intended Audience :: Science/Research
Classifier: License :: OSI Approved :: Apache Software License
Classifier: Natural Language :: English
Classifier: Programming Language :: Python
Classifier: Programming Language :: Python :: 3.11
Classifier: Programming Language :: Python :: 3.12
Classifier: Programming Language :: Python :: 3.13
Classifier: Topic :: Scientific/Engineering
Classifier: Topic :: Scientific/Engineering :: Physics
Classifier: Topic :: Software Development :: Libraries
Classifier: Topic :: Utilities
Requires-Python: >=3.11
License-File: LICENSE
Requires-Dist: fmu-config>=1.1.0
Requires-Dist: fmu-datamodels~=0.16.0
Requires-Dist: numpy
Requires-Dist: pandas
Requires-Dist: pyarrow
Requires-Dist: pydantic
Requires-Dist: PyYAML
Requires-Dist: xtgeo>=2.16
Requires-Dist: fmu-sumo
Requires-Dist: jsonschema
Provides-Extra: dev
Requires-Dist: coverage>=4.1; extra == "dev"
Requires-Dist: ert>=15; extra == "dev"
Requires-Dist: hypothesis; extra == "dev"
Requires-Dist: jsonschema; extra == "dev"
Requires-Dist: mypy; extra == "dev"
Requires-Dist: pandas-stubs; extra == "dev"
Requires-Dist: pyarrow-stubs; extra == "dev"
Requires-Dist: pydocstyle; extra == "dev"
Requires-Dist: pyqt6<6.10.0; extra == "dev"
Requires-Dist: pytest; extra == "dev"
Requires-Dist: pytest-cov; extra == "dev"
Requires-Dist: pytest-mock; extra == "dev"
Requires-Dist: pytest-runner; extra == "dev"
Requires-Dist: pytest-xdist; extra == "dev"
Requires-Dist: rstcheck; extra == "dev"
Requires-Dist: ruff; extra == "dev"
Requires-Dist: types-PyYAML; extra == "dev"
Requires-Dist: types-requests; extra == "dev"
Provides-Extra: docs
Requires-Dist: Sphinx; extra == "docs"
Requires-Dist: autoapi; extra == "docs"
Requires-Dist: autodoc-pydantic>=2.0.0; extra == "docs"
Requires-Dist: furo; extra == "docs"
Requires-Dist: myst-parser; extra == "docs"
Requires-Dist: pydocstyle; extra == "docs"
Requires-Dist: sphinx-autodoc-typehints; extra == "docs"
Requires-Dist: sphinx-copybutton; extra == "docs"
Requires-Dist: sphinx-togglebutton; extra == "docs"
Requires-Dist: sphinxcontrib-apidoc; extra == "docs"
Requires-Dist: urllib3<1.27; extra == "docs"
Dynamic: license-file
